README.md
setup.py
nhlapi/__init__.py
nhlapi/nhlapi.py
nhlapi.egg-info/PKG-INFO
nhlapi.egg-info/SOURCES.txt
nhlapi.egg-info/dependency_links.txt
nhlapi.egg-info/requires.txt
nhlapi.egg-info/top_level.txt
nhlapi/beans/__init__.py
nhlapi/beans/game.py
nhlapi/beans/live_game_data.py
nhlapi/beans/team.py
nhlapi/constants/__init__.py
nhlapi/constants/team_constants.py
nhlapi/constants/url_constants.py
nhlapi/data_source/__init__.py
nhlapi/data_source/api.py
nhlapi/data_source/json_api.py
nhlapi/services/__init__.py
nhlapi/services/game_service.py
nhlapi/services/team_service.py
nhlapi/util/__init__.py
nhlapi/util/time_util.py