Metadata-Version: 1.0
Name: nhlapi
Version: 0.0.3
Summary: an API used to parse JSON data from the NHL website
Home-page: https://github.com/rchristilaw/nhlapi
Author: Ryan Christilaw
Author-email: ryan.christilaw@gmail.com
License: MIT
Keywords: nhl scores
Platform: UNKNOWN
